exprlens/__init__.py
exprlens/lens.py
exprlens/valid.py
exprlens-0.0.6.dist-info/LICENSE
exprlens-0.0.6.dist-info/METADATA
exprlens-0.0.6.dist-info/WHEEL
exprlens-0.0.6.dist-info/RECORD
