Metadata-Version: 2.3
Name: exprlens
Version: 0.0.6
Summary: Lenses from python expressions.
License: Artistic License
Author: Piotr Mardziel
Author-email: piotrm@gmail.com
Requires-Python: >=3.9,<4.0
Classifier: License :: OSI Approved :: Artistic License
Classifier: License :: Other/Proprietary License
Classifier: Operating System :: OS Independent
Classifier: Programming Language :: Python :: 3
Classifier: Programming Language :: Python :: 3.9
Classifier: Programming Language :: Python :: 3.10
Classifier: Programming Language :: Python :: 3.11
Classifier: Programming Language :: Python :: 3.12
Classifier: Programming Language :: Python :: 3.13
Requires-Dist: pydantic (>=2.0,<3.0)
Requires-Dist: typeguard (>=4.3,<5.0)
Project-URL: Homepage, https://github.com/piotrm0/exprlens
